hugdown/__init__.py
hugdown/logger_init.py
hugdown/utils.py
hugdown-0.2.2.dist-info/LICENSE
hugdown-0.2.2.dist-info/METADATA
hugdown-0.2.2.dist-info/WHEEL
hugdown-0.2.2.dist-info/RECORD
