Metadata-Version: 2.1
Name: hugdown
Version: 0.2.2
Summary: A HuggingFace file downloader that retries automatically.
License: MIT
Author: Lingxi Li
Author-email: lilingxi01@gmail.com
Requires-Python: >=3.8
Classifier: License :: OSI Approved :: MIT License
Classifier: Programming Language :: Python :: 3
Classifier: Programming Language :: Python :: 3.8
Classifier: Programming Language :: Python :: 3.9
Classifier: Programming Language :: Python :: 3.10
Classifier: Programming Language :: Python :: 3.11
Classifier: Programming Language :: Python :: 3.12
Requires-Dist: huggingface-hub (>=0.14.1,<0.15.0)
Requires-Dist: psutil (>=5.9.5,<6.0.0)
Requires-Dist: tqdm (>=4.65.0,<5.0.0)
Requires-Dist: urllib3 (>=2.0.2,<3.0.0)
